gpu_list/__init__.py
gpu_list/main.py
gpu_list/pci.ids
gpu_list-0.1.0.dist-info/licenses/LICENSE
gpu_list-0.1.0.dist-info/METADATA
gpu_list-0.1.0.dist-info/WHEEL
gpu_list-0.1.0.dist-info/entry_points.txt
gpu_list-0.1.0.dist-info/top_level.txt
gpu_list-0.1.0.dist-info/RECORD
