Metadata-Version: 2.4
Name: gpu_list
Version: 0.1.0
Summary: List GPUs and VRAM amounts in Windows and Linux
Author: electroglyph
License-Expression: BSD-2-Clause
Project-URL: Homepage, https://github.com/electroglyph/gpu_list
Project-URL: Repository, https://github.com/electroglyph/gpu_list
Classifier: Programming Language :: Python :: 3
Classifier: Operating System :: OS Independent
Requires-Python: >=3.8
License-File: LICENSE
Requires-Dist: prettytable
Dynamic: license-file
